gCodeGen/Collector.py
gCodeGen/__init__.py
gCodeGen/agCodeLexer.py
gCodeGen/agCodeParser.py
gCodeGen/agCodeVisitor.py
gCodeGen/gCodeGen.py
gCodeGen-1.1.1.dist-info/LICENSE
gCodeGen-1.1.1.dist-info/METADATA
gCodeGen-1.1.1.dist-info/WHEEL
gCodeGen-1.1.1.dist-info/top_level.txt
gCodeGen-1.1.1.dist-info/RECORD
