Metadata-Version: 2.1
Name: gCodeGen
Version: 1.1.1
Summary: A simple domain language to generate G-Code
Home-page: https://github.com/WebiusD/gCodeGenerator
Author: Dennis Schwebius
Author-email: schwebius.dennis@web.de
License: UNKNOWN
Project-URL: Parsing Tool, https://github.com/antlr/antlr4
Platform: UNKNOWN
Classifier: Programming Language :: Python :: 3
Classifier: License :: OSI Approved :: MIT License
Classifier: Operating System :: OS Independent
Requires-Python: >=3.7
License-File: LICENSE
Requires-Dist: antlr4-python3-runtime
